{"nodes": [{"id": "bmad_cis_config", "label": "BMAD CIS Module Configuration", "file_type": "document", "source_file": "_bmad/cis/config.yaml", "source_location": null, "source_url": null, "captured_at": "2026-05-07", "author": "Vuonglq01685", "contributor": null}], "edges": [{"source": "bmad_cis_config", "target": "rationale_bmad_v660_framework", "relation": "conceptually_related_to", "confidence": "INFERRED", "confidence_score": 0.95, "source_file": "_bmad/cis/config.yaml", "source_location": null, "weight": 0.9}], "hyperedges": []}